xmos_ai_tools/xcore_tflm_host_interpreter/__init__.py
xmos_ai_tools/xcore_tflm_host_interpreter/exceptions.py
xmos_ai_tools/xcore_tflm_host_interpreter/libs/macos/xtflm_python.1.0.1.dylib
xmos_ai_tools/xcore_tflm_host_interpreter/libs/macos/xtflm_python.dylib
xmos_ai_tools/xformer/__init__.py
xmos_ai_tools_beta-0.1.5.dev20220320.data/data/bin/xcore-opt
xmos_ai_tools_beta-0.1.5.dev20220320.dist-info/LICENSE.rst
xmos_ai_tools_beta-0.1.5.dev20220320.dist-info/METADATA
xmos_ai_tools_beta-0.1.5.dev20220320.dist-info/WHEEL
xmos_ai_tools_beta-0.1.5.dev20220320.dist-info/top_level.txt
xmos_ai_tools_beta-0.1.5.dev20220320.dist-info/RECORD
