Metadata-Version: 2.1
Name: xmos-ai-tools-beta
Version: 0.1.5.dev20220320
Summary: XMOS AI Tools
Home-page: https://github.com/xmos/ai_tools
Author: XMOS
Author-email: support@xmos.com
License: LICENSE.txt
Keywords: tensorflow binarized neural networks
Platform: UNKNOWN
Classifier: License :: Other/Proprietary License
Classifier: Development Status :: 4 - Beta
Classifier: Intended Audience :: Developers
Classifier: Intended Audience :: Education
Classifier: Intended Audience :: Science/Research
Classifier: Programming Language :: Python :: 3
Classifier: Programming Language :: Python :: 3 :: Only
Classifier: Programming Language :: Python :: 3.7
Classifier: Programming Language :: Python :: 3.8
Classifier: Programming Language :: Python :: 3.9
Classifier: Topic :: Scientific/Engineering
Classifier: Topic :: Scientific/Engineering :: Mathematics
Classifier: Topic :: Scientific/Engineering :: Artificial Intelligence
Classifier: Topic :: Software Development
Classifier: Topic :: Software Development :: Libraries
Classifier: Topic :: Software Development :: Libraries :: Python Modules
Requires-Python: >=3.7
Requires-Dist: numpy (<2.0)
